{
  "pins": [
    {
      "id": "Qpjl_dXQrD8",
      "alt_description": "gray tabby kitten on tree",
      "url": "https://images.unsplash.com/photo-1503844281047-cf42eade5ca5?crop=entropy&cs=tinysrgb&fit=max&fm=jpg&ixid=MnwyMzc4Mzl8MHwxfHNlYXJjaHwxN3x8Y2F0c3xlbnwwfHx8fDE2MjYxMjY5NjI&ixlib=rb-1.2.1&q=80&w=400",
      "link": "https://unsplash.com/photos/Qpjl_dXQrD8"
    },
    {
      "id": "pZZJwwNPy2k",
      "alt_description": "five cupcakes beside cake",
      "url": "https://images.unsplash.com/photo-1562777717-dc6984f65a63?crop=entropy&cs=tinysrgb&fit=max&fm=jpg&ixid=MnwyMzc4Mzl8MHwxfHNlYXJjaHwxMnx8Y2FrZXxlbnwwfHx8fDE2MjYxMjg1OTE&ixlib=rb-1.2.1&q=80&w=400",
      "link": "https://unsplash.com/photos/pZZJwwNPy2k"
    },
    {
      "id": "9J7sHieVFi0",
      "alt_description": "person pouring chocolate powder on cake",
      "url": "https://images.unsplash.com/photo-1512223792601-592a9809eed4?crop=entropy&cs=tinysrgb&fit=max&fm=jpg&ixid=MnwyMzc4Mzl8MHwxfHNlYXJjaHwxN3x8Y2FrZXxlbnwwfHx8fDE2MjYxMjg1OTE&ixlib=rb-1.2.1&q=80&w=400",
      "link": "https://unsplash.com/photos/9J7sHieVFi0"
    },
    {
      "id": "TiSLq6Gbftg",
      "alt_description": "white and pink unicorn cake on a pink stand",
      "url": "https://images.unsplash.com/photo-1557164158-11e97f2bb220?crop=entropy&cs=tinysrgb&fit=max&fm=jpg&ixid=MnwyMzc4Mzl8MHwxfHNlYXJjaHwyNHx8Y2FrZXxlbnwwfHx8fDE2MjYxMjg1OTE&ixlib=rb-1.2.1&q=80&w=400",
      "link": "https://unsplash.com/photos/TiSLq6Gbftg"
    },
    {
      "id": "jDJ14ALPIK4",
      "alt_description": "black cat in tilt shift lens",
      "url": "https://images.unsplash.com/photo-1593096298921-b14f39368376?crop=entropy&cs=tinysrgb&fit=max&fm=jpg&ixid=MnwyMzc4Mzl8MHwxfHNlYXJjaHw4NHx8YW5pbWFsc3xlbnwwfHx8fDE2MjYxMjg2MTU&ixlib=rb-1.2.1&q=80&w=400",
      "link": "https://unsplash.com/photos/jDJ14ALPIK4"
    },
    {
      "id": "7HKdb6i3afk",
      "alt_description": "lion lying on green grass during daytime",
      "url": "https://images.unsplash.com/photo-1607274134639-043342705e6f?crop=entropy&cs=tinysrgb&fit=max&fm=jpg&ixid=MnwyMzc4Mzl8MHwxfHNlYXJjaHwxMDl8fGFuaW1hbHN8ZW58MHx8fHwxNjI2MTI4NjE1&ixlib=rb-1.2.1&q=80&w=400",
      "link": "https://unsplash.com/photos/7HKdb6i3afk"
    },
    {
      "id": "pdALzg0yN-8",
      "alt_description": "cat sleeping on bed",
      "url": "https://images.unsplash.com/photo-1548802673-380ab8ebc7b7?crop=entropy&cs=tinysrgb&fit=max&fm=jpg&ixid=MnwyMzc4Mzl8MHwxfHNlYXJjaHwxfHxjYXRzfGVufDB8fHx8MTYyNjEyNjQwNw&ixlib=rb-1.2.1&q=80&w=400",
      "link": "https://unsplash.com/photos/pdALzg0yN-8"
    },
    {
      "id": "uy5t-CJuIK4",
      "alt_description": "white cat sleeps under white comforter",
      "url": "https://images.unsplash.com/photo-1541781774459-bb2af2f05b55?crop=entropy&cs=tinysrgb&fit=max&fm=jpg&ixid=MnwyMzc4Mzl8MHwxfHNlYXJjaHwxNHx8Y2F0c3xlbnwwfHx8fDE2MjYxMjY5NjI&ixlib=rb-1.2.1&q=80&w=400",
      "link": "https://unsplash.com/photos/uy5t-CJuIK4"
    },
    {
      "id": "21NRDbMJF94",
      "alt_description": "short-fur brown and white cat resting on floor",
      "url": "https://images.unsplash.com/photo-1574063413132-354db9f190fd?crop=entropy&cs=tinysrgb&fit=max&fm=jpg&ixid=MnwyMzc4Mzl8MHwxfHNlYXJjaHwzOHx8Y2F0c3xlbnwwfHx8fDE2MjYyMDQ5MTI&ixlib=rb-1.2.1&q=80&w=400",
      "link": "https://unsplash.com/photos/21NRDbMJF94"
    },
    {
      "id": "DTSDD968Mpw",
      "alt_description": "short-coated beige puppy",
      "url": "https://images.unsplash.com/photo-1510337550647-e84f83e341ca?crop=entropy&cs=tinysrgb&fit=max&fm=jpg&ixid=MnwyMzc4Mzl8MHwxfHNlYXJjaHw1Nnx8cHVwcGllc3xlbnwwfHx8fDE2MjYyMDYzMDg&ixlib=rb-1.2.1&q=80&w=400",
      "link": "https://unsplash.com/photos/DTSDD968Mpw"
    },
    {
      "id": "2JcixB1Ky3I",
      "alt_description": "kittens in basket",
      "url": "https://images.unsplash.com/photo-1570824104453-508955ab713e?crop=entropy&cs=tinysrgb&fit=max&fm=jpg&ixid=MnwyMzc4Mzl8MHwxfHNlYXJjaHwzfHxjYXRzfGVufDB8fHx8MTYyNjIxMjgzNw&ixlib=rb-1.2.1&q=80&w=400",
      "link": "https://unsplash.com/photos/2JcixB1Ky3I"
    },
    {
      "id": "LIEQsu5JuoM",
      "alt_description": "woman standing on dock",
      "url": "https://images.unsplash.com/photo-1540324155974-7523202daa3f?crop=entropy&cs=tinysrgb&fit=max&fm=jpg&ixid=MnwyMzc4Mzl8MHwxfHNlYXJjaHwxfHxkYW5jZXxlbnwwfHx8fDE2MjYyMTU3MzM&ixlib=rb-1.2.1&q=80&w=400",
      "link": "https://unsplash.com/photos/LIEQsu5JuoM"
    }
  ]
}